Metadata-Version: 2.1
Name: ashesdistribution
Version: 0.0.1
Summary: This is a homework package in Udacity
Home-page: UNKNOWN
License: UNKNOWN
Platform: UNKNOWN
License-File: LICENSE.txt
